fluddy/__init__.py
fluddy/bud.py
fluddy/cli.py
fluddy/create.py
fluddy/flask_port.py
fluddy/launcher.py
fluddy/logs.py
fluddy/test.py
fluddy/user_os.py
fluddy-0.0.3.dist-info/DESCRIPTION.rst
fluddy-0.0.3.dist-info/METADATA
fluddy-0.0.3.dist-info/RECORD
fluddy-0.0.3.dist-info/WHEEL
fluddy-0.0.3.dist-info/entry_points.txt
fluddy-0.0.3.dist-info/metadata.json
fluddy-0.0.3.dist-info/top_level.txt
fluddy-0.0.3.dist-info/zip-safe
