Metadata-Version: 2.0
Name: fluddy
Version: 0.0.3
Summary: Flask Buddy - CLI for managing Flask Apps.
Home-page: https://github.com/jakedent/fluddy
Author: Jacob Dent
Author-email: info@jacobdent.com
License: MIT
Platform: UNKNOWN
Classifier: Development Status :: 5 - Production/Stable
Classifier: Environment :: Console
Classifier: Intended Audience :: Developers
Classifier: License :: OSI Approved :: MIT License
Classifier: Natural Language :: English
Classifier: Operating System :: MacOS
Classifier: Operating System :: Microsoft
Classifier: Operating System :: Unix
Classifier: Programming Language :: Python :: 3.5
Classifier: Programming Language :: Python :: 3.6
Classifier: Programming Language :: Python :: 3.7
Classifier: Programming Language :: Python
Classifier: Topic :: Internet
Classifier: Topic :: Software Development :: Build Tools
Classifier: Topic :: Terminals
Classifier: Topic :: Utilities
Requires-Python: >=3.5
